{"edges": [["UGU", "UGU"], ["GUU", "GUU"], ["UUU", "UUU"], ["UUA", "UUA"], ["UAU", "UAU"], ["AUC", "AUC"], ["UCU", "UCU"], ["CUC", "CUC"], ["UCU", "UCU"], ["CUA", "CUA"], ["UAG", "UAG"], ["AGG", "AGG"], ["GGG", "GGG"], ["GGU", "GGU"], ["GUU", "GUU"], ["UUG", "UUG"], ["UGA", "UGA"], ["GAU", "GAU"], ["AUC", "AUC"], ["UCU", "UCU"], ["CUA", "CUA"], ["UAU", "UAU"], ["AUU", "AUU"], ["UUA", "UUA"], ["UAG", "UAG"], ["AGA", "AGA"], ["GAA", "GAA"], ["AAU", "AAU"], ["AUU", "AUU"], ["UUA", "UUA"], ["UAC", "UAC"], ["ACU", "ACU"], ["CUU", "CUU"], ["UUA", "UUA"], ["UAU", "UAU"], ["AUC", "AUC"], ["UCU", "UCU"], ["CUG", "CUG"], ["UGA", "UGA"], ["GAG", "GAG"], ["AGC", "AGC"], ["GCC", "GCC"], ["CCA", "CCA"], ["CAA", "CAA"], ["AAA", "AAA"], ["AAG", "AAG"], ["AGU", "AGU"], ["GUA", "GUA"], ["UAA", "UAA"], ["AAU", "AAU"], ["AUU", "AUU"], ["UUC", "UUC"], ["UCA", "UCA"], ["CAA", "CAA"], ["AAG", "AAG"], ["AGU", "AGU"], ["GUA", "GUA"], ["UAA", "UAA"], ["AAU", "AAU"], ["AUU", "AUU"], ["UUC", "UUC"], ["UCA", "UCA"], ["CAG", "CAG"], ["AGG", "AGG"], ["GGU", "GGU"], ["GUG", "GUG"], ["UGU", "UGU"], ["GUA", "GUA"], ["UAG", "UAG"], ["AGU", "AGU"], ["GUG", "GUG"], ["UGA", "UGA"], ["GAA", "GAA"], ["AAA", "AAA"], ["AAC", "AAC"], ["AC", "AC"], ["C", "C"]], "feature": {"0": "UGU", "1": "GUU", "2": "UUU", "3": "UUA", "4": "UAU", "5": "AUC", "6": "UCU", "7": "CUC", "8": "UCU", "9": "CUA", "10": "UAG", "11": "AGG", "12": "GGG", "13": "GGU", "14": "GUU", "15": "UUG", "16": "UGA", "17": "GAU", "18": "AUC", "19": "UCU", "20": "CUA", "21": "UAU", "22": "AUU", "23": "UUA", "24": "UAG", "25": "AGA", "26": "GAA", "27": "AAU", "28": "AUU", "29": "UUA", "30": "UAC", "31": "ACU", "32": "CUU", "33": "UUA", "34": "UAU", "35": "AUC", "36": "UCU", "37": "CUG", "38": "UGA", "39": "GAG", "40": "AGC", "41": "GCC", "42": "CCA", "43": "CAA", "44": "AAA", "45": "AAG", "46": "AGU", "47": "GUA", "48": "UAA", "49": "AAU", "50": "AUU", "51": "UUC", "52": "UCA", "53": "CAA", "54": "AAG", "55": "AGU", "56": "GUA", "57": "UAA", "58": "AAU", "59": "AUU", "60": "UUC", "61": "UCA", "62": "CAG", "63": "AGG", "64": "GGU", "65": "GUG", "66": "UGU", "67": "GUA", "68": "UAG", "69": "AGU", "70": "GUG", "71": "UGA", "72": "GAA", "73": "AAA", "74": "AAC", "75": "AC", "76": "C"}}