{"edges": [["UCU", "UCU"], ["CUA", "CUA"], ["UAU", "UAU"], ["AUU", "AUU"], ["UUU", "UUU"], ["UUG", "UUG"], ["UGU", "UGU"], ["GUC", "GUC"], ["UCU", "UCU"], ["CUU", "CUU"], ["UUA", "UUA"], ["UAG", "UAG"], ["AGG", "AGG"], ["GGU", "GGU"], ["GUG", "GUG"], ["UGA", "UGA"], ["GAG", "GAG"], ["AGC", "AGC"], ["GCU", "GCU"], ["CUA", "CUA"], ["UAA", "UAA"], ["AAA", "AAA"], ["AAU", "AAU"], ["AUG", "AUG"], ["UGU", "UGU"], ["GUG", "GUG"], ["UGU", "UGU"], ["GUG", "GUG"], ["UGC", "UGC"], ["GCU", "GCU"], ["CUG", "CUG"], ["UGG", "UGG"], ["GGG", "GGG"], ["GGA", "GGA"], ["GAC", "GAC"], ["ACA", "ACA"], ["CAC", "CAC"], ["ACA", "ACA"], ["CAU", "CAU"], ["AUU", "AUU"], ["UUU", "UUU"], ["UUG", "UUG"], ["UGA", "UGA"], ["GAG", "GAG"], ["AGC", "AGC"], ["GCC", "GCC"], ["CCA", "CCA"], ["CAA", "CAA"], ["AAA", "AAA"], ["AAU", "AAU"], ["AUG", "AUG"], ["UGU", "UGU"], ["GUC", "GUC"], ["UCC", "UCC"], ["CCC", "CCC"], ["CCA", "CCA"], ["CAG", "CAG"], ["AGC", "AGC"], ["GCA", "GCA"], ["CAC", "CAC"], ["ACA", "ACA"], ["CAC", "CAC"], ["ACA", "ACA"], ["CAU", "CAU"], ["AUU", "AUU"], ["UUU", "UUU"], ["UUA", "UUA"], ["UAG", "UAG"], ["AGC", "AGC"], ["GCU", "GCU"], ["CUC", "CUC"], ["UCA", "UCA"], ["CAC", "CAC"], ["ACA", "ACA"], ["CAU", "CAU"], ["AUA", "AUA"], ["UAA", "UAA"], ["AAG", "AAG"], ["AGA", "AGA"], ["GAA", "GAA"], ["AAA", "AAA"], ["AAA", "AAA"], ["AAA", "AAA"], ["AAU", "AAU"], ["AUG", "AUG"], ["UGG", "UGG"], ["GGA", "GGA"], ["GAC", "GAC"], ["ACU", "ACU"], ["CUC", "CUC"], ["UCU", "UCU"], ["CUA", "CUA"], ["UAG", "UAG"], ["AGU", "AGU"], ["GU", "GU"], ["U", "U"]], "feature": {"0": "UCU", "1": "CUA", "2": "UAU", "3": "AUU", "4": "UUU", "5": "UUG", "6": "UGU", "7": "GUC", "8": "UCU", "9": "CUU", "10": "UUA", "11": "UAG", "12": "AGG", "13": "GGU", "14": "GUG", "15": "UGA", "16": "GAG", "17": "AGC", "18": "GCU", "19": "CUA", "20": "UAA", "21": "AAA", "22": "AAU", "23": "AUG", "24": "UGU", "25": "GUG", "26": "UGU", "27": "GUG", "28": "UGC", "29": "GCU", "30": "CUG", "31": "UGG", "32": "GGG", "33": "GGA", "34": "GAC", "35": "ACA", "36": "CAC", "37": "ACA", "38": "CAU", "39": "AUU", "40": "UUU", "41": "UUG", "42": "UGA", "43": "GAG", "44": "AGC", "45": "GCC", "46": "CCA", "47": "CAA", "48": "AAA", "49": "AAU", "50": "AUG", "51": "UGU", "52": "GUC", "53": "UCC", "54": "CCC", "55": "CCA", "56": "CAG", "57": "AGC", "58": "GCA", "59": "CAC", "60": "ACA", "61": "CAC", "62": "ACA", "63": "CAU", "64": "AUU", "65": "UUU", "66": "UUA", "67": "UAG", "68": "AGC", "69": "GCU", "70": "CUC", "71": "UCA", "72": "CAC", "73": "ACA", "74": "CAU", "75": "AUA", "76": "UAA", "77": "AAG", "78": "AGA", "79": "GAA", "80": "AAA", "81": "AAA", "82": "AAA", "83": "AAU", "84": "AUG", "85": "UGG", "86": "GGA", "87": "GAC", "88": "ACU", "89": "CUC", "90": "UCU", "91": "CUA", "92": "UAG", "93": "AGU", "94": "GU", "95": "U"}}