{"edges": [["CUU", "CUU"], ["UUC", "UUC"], ["UCA", "UCA"], ["CAG", "CAG"], ["AGG", "AGG"], ["GGA", "GGA"], ["GAA", "GAA"], ["AAG", "AAG"], ["AGC", "AGC"], ["GCU", "GCU"], ["CUG", "CUG"], ["UGG", "UGG"], ["GGU", "GGU"], ["GUU", "GUU"], ["UUU", "UUU"], ["UUC", "UUC"], ["UCA", "UCA"], ["CAU", "CAU"], ["AUA", "AUA"], ["UAU", "UAU"], ["AUG", "AUG"], ["UGG", "UGG"], ["GGU", "GGU"], ["GUG", "GUG"], ["UGG", "UGG"], ["GGU", "GGU"], ["GUU", "GUU"], ["UUU", "UUU"], ["UUA", "UUA"], ["UAG", "UAG"], ["AGA", "AGA"], ["GAU", "GAU"], ["AUU", "AUU"], ["UUU", "UUU"], ["UUA", "UUA"], ["UAA", "UAA"], ["AAA", "AAA"], ["AAU", "AAU"], ["AUA", "AUA"], ["UAG", "UAG"], ["AGU", "AGU"], ["GUG", "GUG"], ["UGA", "UGA"], ["GAU", "GAU"], ["AUU", "AUU"], ["UUG", "UUG"], ["UGU", "UGU"], ["GUC", "GUC"], ["UCU", "UCU"], ["CUA", "CUA"], ["UAG", "UAG"], ["AGC", "AGC"], ["GCA", "GCA"], ["CAC", "CAC"], ["ACC", "ACC"], ["CCA", "CCA"], ["CAU", "CAU"], ["AUU", "AUU"], ["UUU", "UUU"], ["UUG", "UUG"], ["UGA", "UGA"], ["GAA", "GAA"], ["AAA", "AAA"], ["AAU", "AAU"], ["AUC", "AUC"], ["UCA", "UCA"], ["CAG", "CAG"], ["AGU", "AGU"], ["GUG", "GUG"], ["UGU", "UGU"], ["GUU", "GUU"], ["UUC", "UUC"], ["UCU", "UCU"], ["CUU", "CUU"], ["UUG", "UUG"], ["UGG", "UGG"], ["GGG", "GGG"], ["GGG", "GGG"], ["GGG", "GGG"], ["GG", "GG"], ["G", "G"]], "feature": {"0": "CUU", "1": "UUC", "2": "UCA", "3": "CAG", "4": "AGG", "5": "GGA", "6": "GAA", "7": "AAG", "8": "AGC", "9": "GCU", "10": "CUG", "11": "UGG", "12": "GGU", "13": "GUU", "14": "UUU", "15": "UUC", "16": "UCA", "17": "CAU", "18": "AUA", "19": "UAU", "20": "AUG", "21": "UGG", "22": "GGU", "23": "GUG", "24": "UGG", "25": "GGU", "26": "GUU", "27": "UUU", "28": "UUA", "29": "UAG", "30": "AGA", "31": "GAU", "32": "AUU", "33": "UUU", "34": "UUA", "35": "UAA", "36": "AAA", "37": "AAU", "38": "AUA", "39": "UAG", "40": "AGU", "41": "GUG", "42": "UGA", "43": "GAU", "44": "AUU", "45": "UUG", "46": "UGU", "47": "GUC", "48": "UCU", "49": "CUA", "50": "UAG", "51": "AGC", "52": "GCA", "53": "CAC", "54": "ACC", "55": "CCA", "56": "CAU", "57": "AUU", "58": "UUU", "59": "UUG", "60": "UGA", "61": "GAA", "62": "AAA", "63": "AAU", "64": "AUC", "65": "UCA", "66": "CAG", "67": "AGU", "68": "GUG", "69": "UGU", "70": "GUU", "71": "UUC", "72": "UCU", "73": "CUU", "74": "UUG", "75": "UGG", "76": "GGG", "77": "GGG", "78": "GGG", "79": "GG", "80": "G"}}