{"edges": [["GU", "GU"], ["UA", "UA"], ["AG", "AG"], ["GU", "GU"], ["UC", "UC"], ["CA", "CA"], ["AG", "AG"], ["GU", "GU"], ["UA", "UA"], ["AG", "AG"], ["GU", "GU"], ["UU", "UU"], ["UG", "UG"], ["GG", "GG"], ["GG", "GG"], ["GG", "GG"], ["GG", "GG"], ["GG", "GG"], ["GU", "GU"], ["UG", "UG"], ["GG", "GG"], ["GG", "GG"], ["GA", "GA"], ["AA", "AA"], ["AC", "AC"], ["CG", "CG"], ["GG", "GG"], ["GC", "GC"], ["CU", "CU"], ["UU", "UU"], ["UC", "UC"], ["CA", "CA"], ["AU", "AU"], ["UA", "UA"], ["AC", "AC"], ["CA", "CA"], ["AG", "AG"], ["GG", "GG"], ["GA", "GA"], ["AG", "AG"], ["GU", "GU"], ["UU", "UU"], ["UG", "UG"], ["GA", "GA"], ["AU", "AU"], ["UG", "UG"], ["GC", "GC"], ["CA", "CA"], ["AC", "AC"], ["CA", "CA"], ["AG", "AG"], ["GU", "GU"], ["UU", "UU"], ["UA", "UA"], ["AU", "AU"], ["UC", "UC"], ["CC", "CC"], ["CA", "CA"], ["AG", "AG"], ["GC", "GC"], ["CU", "CU"], ["UC", "UC"], ["CC", "CC"], ["CU", "CU"], ["UA", "UA"], ["AU", "AU"], ["UA", "UA"], ["AU", "AU"], ["UG", "UG"], ["GA", "GA"], ["AU", "AU"], ["UG", "UG"], ["GC", "GC"], ["CC", "CC"], ["CU", "CU"], ["UU", "UU"], ["UU", "UU"], ["UC", "UC"], ["CU", "CU"], ["UU", "UU"], ["UC", "UC"], ["CA", "CA"], ["AU", "AU"], ["UC", "UC"], ["CC", "CC"], ["CC", "CC"], ["CC", "CC"], ["CU", "CU"], ["UU", "UU"], ["UC", "UC"], ["CA", "CA"], ["AA", "AA"], ["A", "A"]], "feature": {"0": "GU", "1": "UA", "2": "AG", "3": "GU", "4": "UC", "5": "CA", "6": "AG", "7": "GU", "8": "UA", "9": "AG", "10": "GU", "11": "UU", "12": "UG", "13": "GG", "14": "GG", "15": "GG", "16": "GG", "17": "GG", "18": "GU", "19": "UG", "20": "GG", "21": "GG", "22": "GA", "23": "AA", "24": "AC", "25": "CG", "26": "GG", "27": "GC", "28": "CU", "29": "UU", "30": "UC", "31": "CA", "32": "AU", "33": "UA", "34": "AC", "35": "CA", "36": "AG", "37": "GG", "38": "GA", "39": "AG", "40": "GU", "41": "UU", "42": "UG", "43": "GA", "44": "AU", "45": "UG", "46": "GC", "47": "CA", "48": "AC", "49": "CA", "50": "AG", "51": "GU", "52": "UU", "53": "UA", "54": "AU", "55": "UC", "56": "CC", "57": "CA", "58": "AG", "59": "GC", "60": "CU", "61": "UC", "62": "CC", "63": "CU", "64": "UA", "65": "AU", "66": "UA", "67": "AU", "68": "UG", "69": "GA", "70": "AU", "71": "UG", "72": "GC", "73": "CC", "74": "CU", "75": "UU", "76": "UU", "77": "UC", "78": "CU", "79": "UU", "80": "UC", "81": "CA", "82": "AU", "83": "UC", "84": "CC", "85": "CC", "86": "CC", "87": "CU", "88": "UU", "89": "UC", "90": "CA", "91": "AA", "92": "A"}}