{"edges": [["AC", "AC"], ["CC", "CC"], ["CU", "CU"], ["UU", "UU"], ["UU", "UU"], ["UC", "UC"], ["CC", "CC"], ["CA", "CA"], ["AG", "AG"], ["GC", "GC"], ["CU", "CU"], ["UC", "UC"], ["CA", "CA"], ["AU", "AU"], ["UC", "UC"], ["CC", "CC"], ["CC", "CC"], ["CA", "CA"], ["AC", "AC"], ["CC", "CC"], ["CU", "CU"], ["UC", "UC"], ["CU", "CU"], ["UG", "UG"], ["GC", "GC"], ["CC", "CC"], ["CA", "CA"], ["AC", "AC"], ["CC", "CC"], ["CA", "CA"], ["AA", "AA"], ["AA", "AA"], ["AA", "AA"], ["AC", "AC"], ["CA", "CA"], ["AC", "AC"], ["CU", "CU"], ["UC", "UC"], ["CA", "CA"], ["AU", "AU"], ["UC", "UC"], ["CG", "CG"], ["GC", "GC"], ["CG", "CG"], ["GG", "GG"], ["GG", "GG"], ["GG", "GG"], ["GU", "GU"], ["UC", "UC"], ["CA", "CA"], ["AG", "AG"], ["GA", "GA"], ["AG", "AG"], ["GG", "GG"], ["GG", "GG"], ["GA", "GA"], ["AG", "AG"], ["GU", "GU"], ["UG", "UG"], ["GC", "GC"], ["CC", "CC"], ["CA", "CA"], ["AA", "AA"], ["AA", "AA"], ["AA", "AA"], ["AA", "AA"], ["AA", "AA"], ["AG", "AG"], ["GG", "GG"], ["GU", "GU"], ["UA", "UA"], ["AA", "AA"], ["A", "A"]], "feature": {"0": "AC", "1": "CC", "2": "CU", "3": "UU", "4": "UU", "5": "UC", "6": "CC", "7": "CA", "8": "AG", "9": "GC", "10": "CU", "11": "UC", "12": "CA", "13": "AU", "14": "UC", "15": "CC", "16": "CC", "17": "CA", "18": "AC", "19": "CC", "20": "CU", "21": "UC", "22": "CU", "23": "UG", "24": "GC", "25": "CC", "26": "CA", "27": "AC", "28": "CC", "29": "CA", "30": "AA", "31": "AA", "32": "AA", "33": "AC", "34": "CA", "35": "AC", "36": "CU", "37": "UC", "38": "CA", "39": "AU", "40": "UC", "41": "CG", "42": "GC", "43": "CG", "44": "GG", "45": "GG", "46": "GG", "47": "GU", "48": "UC", "49": "CA", "50": "AG", "51": "GA", "52": "AG", "53": "GG", "54": "GG", "55": "GA", "56": "AG", "57": "GU", "58": "UG", "59": "GC", "60": "CC", "61": "CA", "62": "AA", "63": "AA", "64": "AA", "65": "AA", "66": "AA", "67": "AG", "68": "GG", "69": "GU", "70": "UA", "71": "AA", "72": "A"}}